python_active_directory.libs/libk5crypto-bf93770e.so.3.1
python_active_directory.libs/libcom_err-ec8bb354.so.2.1
python_active_directory.libs/libkeyutils-d695bd83.so.1.9
python_active_directory.libs/libkrb5-9554a061.so.3.3
python_active_directory.libs/libkrb5support-b3d5b8b2.so.0.1
activedirectory/__init__.py
activedirectory/core/locate.py
activedirectory/core/object.py
activedirectory/core/creds.py
activedirectory/core/exception.py
activedirectory/core/constant.py
activedirectory/core/client.py
activedirectory/core/__init__.py
activedirectory/protocol/ldapfilter.py
activedirectory/protocol/ldapfilter_tab.py
activedirectory/protocol/netlogon.py
activedirectory/protocol/krb5.cpython-311-x86_64-linux-musl.so
activedirectory/protocol/__init__.py
activedirectory/protocol/asn1.py
activedirectory/protocol/ldap.py
activedirectory/util/misc.py
activedirectory/util/parser.py
activedirectory/util/log.py
activedirectory/util/__init__.py
activedirectory/util/compat.py
python_active_directory-2.0.1.dist-info/RECORD
python_active_directory-2.0.1.dist-info/METADATA
python_active_directory-2.0.1.dist-info/LICENSE
python_active_directory-2.0.1.dist-info/WHEEL
python_active_directory-2.0.1.dist-info/top_level.txt
python_active_directory-2.0.1.dist-info/AUTHORS
