Metadata-Version: 2.1
Name: python-active-directory
Version: 2.0.1
Summary: An Active Directory client library for Python
Home-page: https://github.com/theatlantic/python-active-directory
Author: Geert Jansen
Author-email: programmers@theatlantic.com
Maintainer: The Atlantic
Maintainer-email: programmers@theatlantic.com
License: MIT
Classifier: Development Status :: 5 - Production/Stable
Classifier: Intended Audience :: Developers
Classifier: License :: OSI Approved :: MIT License
Classifier: Programming Language :: Python
Classifier: Programming Language :: Python :: 3
Classifier: Programming Language :: Python :: 3 :: Only
Classifier: Programming Language :: Python :: 3.7
Classifier: Programming Language :: Python :: 3.8
License-File: LICENSE
License-File: AUTHORS
Requires-Dist: python-ldap (>=3.0)
Requires-Dist: dnspython
Requires-Dist: ply (>=3.8)
